simpleaitranslator/__init__.py
simpleaitranslator/exceptions.py
simpleaitranslator/translator.py
simpleaitranslator/utils/__init__.py
simpleaitranslator/utils/enums.py
simpleaitranslator/utils/iso639_1.py
simpleaitranslator/utils/text_splitter.py
simpleaitranslator-2.3.6.dist-info/LICENSE
simpleaitranslator-2.3.6.dist-info/METADATA
simpleaitranslator-2.3.6.dist-info/WHEEL
simpleaitranslator-2.3.6.dist-info/RECORD
