Metadata-Version: 2.1
Name: simpleaitranslator
Version: 2.3.6
Summary: A Python library for language detection and translation using OpenAI's GPT-4o.
Author: Adam Pawelek
Author-email: adam.pwk@outlook.com
Requires-Python: >=3.10,<4.0
Classifier: Programming Language :: Python :: 3
Classifier: Programming Language :: Python :: 3.10
Classifier: Programming Language :: Python :: 3.11
Classifier: Programming Language :: Python :: 3.12
Requires-Dist: asyncio (>=3.4.3,<4.0.0)
Requires-Dist: openai (>=1.40.1,<2.0.0)
Requires-Dist: pytest (>=8.2.2,<9.0.0)
Requires-Dist: pytest-asyncio (>=0.23.8,<0.24.0)
Project-URL: documentation, https://github.com/adam-pawelek/SimpleAITranslator
Project-URL: source, https://github.com/adam-pawelek/SimpleAITranslator
